istub/__init__.py
istub/__main__.py
istub/cli.py
istub/config.py
istub/constants.py
istub/exceptions.py
istub/logger.py
istub/main.py
istub/package.py
istub/py.typed
istub/subprocess.py
istub/utils.py
istub/yaml.py
istub/checks/__init__.py
istub/checks/base.py
istub/checks/flake8.py
istub/checks/mypy.py
istub/checks/pyright.py
istub/checks/ruff.py
istub/checks/stubtest.py
istub-0.2.5.dist-info/METADATA
istub-0.2.5.dist-info/WHEEL
istub-0.2.5.dist-info/entry_points.txt
istub-0.2.5.dist-info/licenses/LICENSE
istub-0.2.5.dist-info/RECORD
