Metadata-Version: 2.4
Name: istub
Version: 0.2.5
Summary: Validator for type annotations
Project-URL: Homepage, https://youtype.github.io/istub/
Project-URL: Documentation, https://youtype.github.io/istub/
Project-URL: Repository, https://github.com/youtype/istub
Project-URL: Changelog, https://github.com/youtype/istub/releases
Project-URL: Issues, https://github.com/youtype/istub/issues
Author-email: Vlad Emelianov <vlad.emelianov.nz@gmail.com>
License-Expression: MIT
License-File: LICENSE
Keywords: mypy,pyright,stubs,type-annotations
Classifier: Development Status :: 5 - Production/Stable
Classifier: Environment :: Console
Classifier: License :: OSI Approved :: MIT License
Classifier: Natural Language :: English
Classifier: Operating System :: OS Independent
Classifier: Programming Language :: Python :: 3
Classifier: Programming Language :: Python :: 3 :: Only
Classifier: Programming Language :: Python :: 3.8
Classifier: Programming Language :: Python :: 3.9
Classifier: Programming Language :: Python :: 3.10
Classifier: Programming Language :: Python :: 3.11
Classifier: Programming Language :: Python :: 3.12
Classifier: Programming Language :: Python :: 3.13
Classifier: Programming Language :: Python :: 3.14
Classifier: Programming Language :: Python :: Implementation :: CPython
Classifier: Topic :: Software Development :: Libraries :: Python Modules
Classifier: Typing :: Typed
Requires-Python: >=3.8
Requires-Dist: pyyaml
